[
	{
		"Description": "Starts at spawn, stretches along the entire highway, and ends in the warehouse area.",
		"FinishPos": {
			"Ang": "{0 90 0}",
			"Pos": "[11073 -4014 -11143]"
		},
		"Name": "Highway Sprint",
		"StartPos": {
			"Ang": "{0 0 0}",
			"Pos": "[-1143 1169 -11143]"
		},
		"BlockSpawns": [
			[
				"[-1640 1140 -11143]",
				"{0 0 0}"
			],
			[
				"[-4796 3227 -11143]",
				"{0 90 0}"
			],
			[
				"[-6381 751 -11135]",
				"{0 90 0}"
			],
			[
				"[-10880 -904 -11143]",
				"{0 90 0}"
			],
			[
				"[-6016 -896 -11143]",
				"{0 90 0}"
			],
			[
				"[5057 7707 -11143]",
				"{0 90 0}"
			],
			[
				"[5052 5722 -11143]",
				"{0 90 0}"
			],
			[
				"[4628 6148 -11143]",
				"{0 0 0}"
			],
			[
				"[11383 450 -11143]",
				"{0 0 0}"
			],
			[
				"[9720 438 -11143]",
				"{0 0 0}"
			]
		]
	},
	{
		"Description": "Starts near the big towers and loops around the entire city.",
		"Name": "Big City Loop",
		"StartPos": {
			"Ang": "{0 0 0}",
			"Pos": "[-1025 -5949 -11144]"
		},
		"BlockSpawns": [
			[
				"[-1404 -5557 -11143]",
				"{0 90 0}"
			],
			[
				"[-4094 -5543 -11143]",
				"{0 90 0}"
			],
			[
				"[-4525 -5955 -11143]",
				"{0 0 0}"
			],
			[
				"[-4096 -9039 -11143]",
				"{0 90 0}"
			],
			[
				"[-10472 -5953 -10887]",
				"{0 0 0}"
			],
			[
				"[-10882 -110 -11143]",
				"{0 90 0}"
			],
			[
				"[-6011 -916 -11143]",
				"{0 90 0}"
			],
			[
				"[5057 7732 -11143]",
				"{0 90 0}"
			],
			[
				"[4634 6143 -11143]",
				"{0 0 0}"
			],
			[
				"[5478 6144 -11143]",
				"{0 0 0}"
			],
			[
				"[4658 3057 -11143]",
				"{0 0 0}"
			],
			[
				"[6540 -2158 -11143]",
				"{0 0 0}"
			],
			[
				"[6206 -6372 -11143]",
				"{0 90 0}"
			],
			[
				"[3390 -6308 -11143]",
				"{0 90 0}"
			],
			[
				"[3395 -5501 -11143]",
				"{0 90 0}"
			],
			[
				"[514 -6359 -11143]",
				"{0 90 0}"
			]
		]
	}
]