[
	{
		"Description": "Starts near the abandoned tunnel, stretches through the forest area and underground tunnel, ends near the lake.",
		"FinishPos": {
			"Ang": "{0 0 0}",
			"Pos": "[10024 9592 -431]"
		},
		"Name": "Full Map Circuit",
		"StartPos": {
			"Ang": "{0 180 0}",
			"Pos": "[-2256 -8274 -229]"
		},
		"BlockSpawns": [
			[
				"[2590 -7779 -229]",
				"{0 90 0}"
			],
			[
				"[9183 -8627 -229]",
				"{0 90 0}"
			],
			[
				"[9530 -8251 -229]",
				"{0 0 0}"
			],
			[
				"[9515 -7323 -238]",
				"{0 0 0}"
			],
			[
				"[9714 4712 -322]",
				"{0 90 0}"
			],
			[
				"[1078 1486 -396]",
				"{0 90 0}"
			],
			[
				"[-1329 2385 -230]",
				"{0 90 0}"
			],
			[
				"[-3061 11763 886]",
				"{0 90 0}"
			],
			[
				"[-1336 12816 875]",
				"{0 90 0}"
			]
		]
	}
]